VmLogin/__init__.py
VmLogin/__version__.py
VmLogin/api.py
VmLogin/error.py
VmLogin/local/__init__.py
VmLogin/local/browser.py
VmLogin/online/__init__.py
VmLogin/online/groups.py
VmLogin/online/profiles.py
VmLogin-0.1.3.dist-info/LICENSE
VmLogin-0.1.3.dist-info/METADATA
VmLogin-0.1.3.dist-info/WHEEL
VmLogin-0.1.3.dist-info/top_level.txt
VmLogin-0.1.3.dist-info/RECORD
