Metadata-Version: 2.1
Name: VmLogin
Version: 0.1.3
Summary: 操作VMLogin
Home-page: https://github.com/chensav/VmLogin
Author: chensav
Author-email: chensav@163.com
License: MIT
Classifier: License :: OSI Approved :: MIT License
Classifier: Programming Language :: Python
Classifier: Programming Language :: Python :: 3
Classifier: Programming Language :: Python :: 3.8
Classifier: Programming Language :: Python :: Implementation :: CPython
Classifier: Programming Language :: Python :: Implementation :: PyPy
Requires-Python: >=3.8.16
License-File: LICENSE
Requires-Dist: requests
